pygm/sortedcontainer.py
pygm/sortedlist.py
pygm/__init__.py
pygm/_pygm.cpython-312-x86_64-linux-gnu.so
pygm/sortedset.py
pygm-1.0.1.dist-info/top_level.txt
pygm-1.0.1.dist-info/METADATA
pygm-1.0.1.dist-info/WHEEL
pygm-1.0.1.dist-info/RECORD
pygm-1.0.1.dist-info/LICENSE
pygm.libs/libgomp-a34b3233.so.1.0.0
