Metadata-Version: 2.1
Name: pygm
Version: 1.0.1
Summary: Sorted containers with state-of-the-art query performance and compressed memory usage
Home-page: https://pgm.di.unipi.it/
Author: Giorgio Vinciguerra
Author-email: i@gvdev.com
License: Apache-2.0
Project-URL: Documentation, https://pgm.di.unipi.it/docs/python-reference/
Project-URL: Source, https://github.com/gvinciguerra/PyGM/
Project-URL: Tracker, https://github.com/gvinciguerra/PyGM/issues
Keywords: tree list array btree b+tree vector skiplist container sortedlist sorted set query index data structure
Classifier: License :: OSI Approved :: Apache Software License
Classifier: Development Status :: 5 - Production/Stable
Classifier: Intended Audience :: Developers
Classifier: Intended Audience :: Information Technology
Classifier: Intended Audience :: Science/Research
Classifier: Natural Language :: English
Classifier: Programming Language :: C++
Classifier: Programming Language :: Python :: 3
Classifier: Programming Language :: Python :: 3.3
Classifier: Programming Language :: Python :: 3.4
Classifier: Programming Language :: Python :: 3.5
Classifier: Programming Language :: Python :: 3.6
Classifier: Programming Language :: Python :: 3.7
Classifier: Programming Language :: Python :: 3.8
Classifier: Programming Language :: Python :: 3.9
Classifier: Programming Language :: Python :: 3.10
Classifier: Programming Language :: Python :: 3.11
Classifier: Programming Language :: Python :: 3.12
Classifier: Topic :: Database
Classifier: Topic :: Scientific/Engineering
Classifier: Topic :: Scientific/Engineering :: Artificial Intelligence
Classifier: Topic :: Scientific/Engineering :: Bio-Informatics
Classifier: Topic :: Scientific/Engineering :: Information Analysis
Classifier: Topic :: Software Development
Classifier: Topic :: System
Classifier: Topic :: System :: Archiving :: Compression
Classifier: Topic :: Utilities
License-File: LICENSE
